[
    {
        "id": 1,
        "name": "Bank Banten",
        "type": "LocalBank",
        "customers": [
            {
                "name": "John",
                "ktp": "123456789"
            },
            {
                "name": "Jane",
                "ktp": "012345678"
            }
        ]
    },
    {
        "id": 2,
        "name": "Bank BCA",
        "type": "NationalBank",
        "customers": [
            {
                "name": "Johnny",
                "ktp": "323456789"
            },
            {
                "name": "Jennie",
                "ktp": "512345678"
            },
            {
                "name": "Jake",
                "ktp": "612345678"
            }
        ]
    },
    {
        "id": 3,
        "name": "Bank Mandiri",
        "type": "NationalBank",
        "customers": []
    },
    {
        "id": 4,
        "name": "Bank Mandiri",
        "type": "NationalBank",
        "customers": []
    }
]